<?xml version="1.0" encoding="UTF-8"?>

<ConceptMap xmlns="http://hl7.org/fhir">
  <id value="uscore-to-pcornet-ethnicity"/> 
  <text> 
    <status value="generated"/> 
    <div xmlns="http://www.w3.org/1999/xhtml">
      <h2> Mapping from US Core to PCORNet Ethnicity codes</h2> 
        <p> Mapping from US Core Ethnicity (https://www.hl7.org/fhir/us/core/ValueSet-omb-ethnicity-category.html) to 
        <a>http://hl7.org/fhir/us/cdmh/ValueSet/pcornet-ethnicity</a> 
      </p>
      <div> 
        <p> This concept map defines a mapping from US Core Ethnicity to PCORNet Ethnicity codes.
            For values such as "Patient Refusing to Answer", No Information etc, the mapping software has to map the data absent reason values to the PCORNet Ethnicity codes. 
        </p> 
      </div> 
      <br/> 
      <table class="grid">
        <tr> 
          <td> 
            <b> Source Code</b> 
          </td> 
          <td> 
            <b> Equivalence</b> 
          </td> 
          <td> 
            <b> Destination Code</b> 
          </td> 
        </tr> 
        <tr> 
          <td> 2135-2</td> 
          <td> equal</td> 
          <td> Y</td> 
        </tr> 
        <tr> 
          <td> 2186-5</td> 
          <td> equal</td> 
          <td> N</td> 
        </tr> 
      </table>  
    </div> 
  </text> 
  <url value="http://hl7.org/fhir/us/cdmh/ConceptMap/uscore-to-pcornet-ethnicity"/> 
  <name value="USCoreToPCORNetEthnicity"/> 
  <title value="Mapping from US Core to PCORNet Ethnicity Codes"/>
  <status value="draft"/> 
  <experimental value="false"/> 
  <description value="This concept map defines a mapping from US Core Ethnicity to PCORNet Ethnicity codes."/> 
  <sourceCanonical value="http://hl7.org/fhir/us/core/ValueSet/omb-ethnicity-category"/> 
  <targetCanonical value="http://hl7.org/fhir/us/cdmh/ValueSet/pcornet-ethnicity"/> 
  <group> 
    <element> 
      <code value="2135-2"/> 
      <target> 
        <code value="Y"/> 
        <equivalence value="equal"/> 
      </target> 
    </element> 
    <element> 
      <code value="2186-5"/> 
      <target> 
        <code value="N"/> 
        <equivalence value="equal"/> 
      </target> 
    </element> 
  </group> 
</ConceptMap> 